{
  "generated": "2026-05-19T10:52:16.719Z",
  "viewId": "viw0LjpGuf6lGKLZu",
  "usedBy": [
    {
      "program": "Benefit Plan Claims, Appeals and Litigation",
      "format": "in-person"
    }
  ],
  "recordCount": 2,
  "records": [
    {
      "id": "recR83CSljj6xQkXx",
      "createdTime": "2025-12-15T19:56:02.000Z",
      "fields": {
        "Instance ID": 65,
        "Last Modified": "2026-01-18T15:59:21.000Z",
        "State/Province": "Texas",
        "Registration URL": "https://iaml.com/register.html?format=in-person&program=employee-benefits-law&blocks=2",
        "Program Name": [
          "Benefit Plan Claims, Appeals & Litigation"
        ],
        "Current Enrolled": 0,
        "End Date": "2026-09-16",
        "Show on Website": true,
        "Price Virtual (from PROGRAMS)": [
          575
        ],
        "Min. Capacity": [
          4
        ],
        "Created By": {
          "id": "usrSAo8TcudAuSfA4",
          "email": "mike.jackson@re-vitalized.com",
          "name": "Mike Jackson"
        },
        "Registration Deadline": "2026-09-16T00:00:00.000Z",
        "Price In-Person (from PROGRAMS)": [
          575
        ],
        "Start Date": "2026-09-16",
        "Time Zone": "Central (CT)",
        "Format": "In-Person",
        "Duration (Days)": [
          1
        ],
        "Hero Image URL": "https://storage.googleapis.com/msgsndr/MjGEy0pobNT9su2YJqFI/media/6942c471543282821a15bb9e.jpg",
        "Created Date": "2025-12-15T19:56:02.000Z",
        "Programs": [
          "rec6Jup8xHsP0CzlB"
        ],
        "Instance Name": "\"Benefit Plan Claims, Appeals & Litigation\" - Sep 2026 - Austin",
        "City": "Austin",
        "Enrollment Status": "Low Enrollment"
      }
    },
    {
      "id": "rec8gwGLYMnmU1OuD",
      "createdTime": "2025-12-15T19:56:06.000Z",
      "fields": {
        "Instance ID": 66,
        "Last Modified": "2026-01-18T15:59:21.000Z",
        "State/Province": "Georgia",
        "Registration URL": "https://iaml.com/register.html?format=in-person&program=employee-benefits-law&blocks=2",
        "Program Name": [
          "Benefit Plan Claims, Appeals & Litigation"
        ],
        "Current Enrolled": 0,
        "End Date": "2026-04-22",
        "Show on Website": true,
        "Price Virtual (from PROGRAMS)": [
          575
        ],
        "Min. Capacity": [
          4
        ],
        "Created By": {
          "id": "usrSAo8TcudAuSfA4",
          "email": "mike.jackson@re-vitalized.com",
          "name": "Mike Jackson"
        },
        "Registration Deadline": "2026-04-22T00:00:00.000Z",
        "Price In-Person (from PROGRAMS)": [
          575
        ],
        "Start Date": "2026-04-22",
        "Time Zone": "Eastern (ET)",
        "Format": "In-Person",
        "Duration (Days)": [
          1
        ],
        "Hero Image URL": "https://storage.googleapis.com/msgsndr/MjGEy0pobNT9su2YJqFI/media/6942c4530190afcbbd821451.jpg",
        "Created Date": "2025-12-15T19:56:06.000Z",
        "Programs": [
          "rec6Jup8xHsP0CzlB"
        ],
        "Instance Name": "\"Benefit Plan Claims, Appeals & Litigation\" - Apr 2026 - Atlanta",
        "City": "Atlanta",
        "Enrollment Status": "Closed"
      }
    }
  ]
}